lib/__init__.py
lib/cors.py
cors_finder-1.0.2.dist-info/METADATA
cors_finder-1.0.2.dist-info/WHEEL
cors_finder-1.0.2.dist-info/top_level.txt
cors_finder-1.0.2.dist-info/RECORD
