Metadata-Version: 2.1
Name: cors-finder
Version: 1.0.2
Summary: The cors-finder package is used to find the vulnerable CORS domains
Home-page: UNKNOWN
Author: Hariharan
License: UNKNOWN
Keywords: cors,cors-finder,cors misconfiguration,cors exploit,cors vulnerability
Platform: UNKNOWN
Requires-Dist: colorama
Requires-Dist: requests
